mdx_better_lists/__init__.py
mdx_better_lists/extension.py
mdx_better_lists-1.0.0.dist-info/licenses/LICENSE
mdx_better_lists-1.0.0.dist-info/METADATA
mdx_better_lists-1.0.0.dist-info/WHEEL
mdx_better_lists-1.0.0.dist-info/top_level.txt
mdx_better_lists-1.0.0.dist-info/RECORD
