Metadata-Version: 2.4
Name: mdx_better_lists
Version: 1.0.0
Summary: Python-Markdown extension for better list handling
Author-email: Jimmy Oei <Jamesmontyn@gmail.com>
License: MIT
Project-URL: Homepage, https://github.com/JimmyOei/mdx_better_lists
Project-URL: Repository, https://github.com/JimmyOei/mdx_better_lists
Project-URL: Issues, https://github.com/JimmyOei/mdx_better_lists/issues
Classifier: Development Status :: 3 - Alpha
Classifier: Intended Audience :: Developers
Classifier: License :: OSI Approved :: MIT License
Classifier: Programming Language :: Python :: 3
Classifier: Programming Language :: Python :: 3.8
Classifier: Programming Language :: Python :: 3.9
Classifier: Programming Language :: Python :: 3.10
Classifier: Programming Language :: Python :: 3.11
Classifier: Programming Language :: Python :: 3.12
Classifier: Topic :: Text Processing :: Markup
Requires-Python: >=3.8
License-File: LICENSE
Requires-Dist: markdown>=3.0
Provides-Extra: dev
Requires-Dist: pytest>=7.0; extra == "dev"
Requires-Dist: pytest-cov>=4.0; extra == "dev"
Dynamic: license-file
